bvsr/bvsr.py
bvsr-1.0.10.dist-info/entry_points.txt
bvsr-1.0.10.dist-info/LICENSE
bvsr-1.0.10.dist-info/WHEEL
bvsr-1.0.10.dist-info/METADATA
bvsr-1.0.10.dist-info/RECORD
