Metadata-Version: 2.1
Name: bvsr
Version: 1.0.10
Summary: Batch Video Size Reduction (BVSR) using ffmpeg.
License: GPLv3
Author: abdeladim-s
Author-email: sadiki.abdeladim@gmail.com
Requires-Python: >=3.10,<4.0
Classifier: License :: Other/Proprietary License
Classifier: Programming Language :: Python :: 3
Classifier: Programming Language :: Python :: 3.10
Classifier: Programming Language :: Python :: 3.11
Requires-Dist: ffmpeg-python (>=0.2.0,<0.3.0)
Requires-Dist: gevent (==22.10.2)
Requires-Dist: tqdm (==4.64.1)
